glupredkit/__init__.py
glupredkit/api.py
glupredkit/cli.py
glupredkit/unit_config.json
glupredkit/helpers/__init__.py
glupredkit/helpers/cli.py
glupredkit/helpers/generate_report.py
glupredkit/helpers/model_config_manager.py
glupredkit/helpers/scikit_learn.py
glupredkit/helpers/tf_keras.py
glupredkit/helpers/unit_config_manager.py
glupredkit/metrics/__init__.py
glupredkit/metrics/base_metric.py
glupredkit/metrics/clarke_error_grid.py
glupredkit/metrics/g_mean.py
glupredkit/metrics/glycemia_detection.py
glupredkit/metrics/grmse.py
glupredkit/metrics/mae.py
glupredkit/metrics/mare.py
glupredkit/metrics/mcc_hyper.py
glupredkit/metrics/mcc_hypo.py
glupredkit/metrics/me.py
glupredkit/metrics/mre.py
glupredkit/metrics/parkes_error_grid.py
glupredkit/metrics/parkes_error_grid_exp.py
glupredkit/metrics/pcc.py
glupredkit/metrics/rmse.py
glupredkit/metrics/temporal_gain.py
glupredkit/models/__init__.py
glupredkit/models/base_model.py
glupredkit/models/double_lstm.py
glupredkit/models/loop.py
glupredkit/models/loop_v2.py
glupredkit/models/lstm.py
glupredkit/models/mtl.py
glupredkit/models/naive_linear_regressor.py
glupredkit/models/random_forest.py
glupredkit/models/ridge.py
glupredkit/models/stacked_plsr.py
glupredkit/models/stl.py
glupredkit/models/svr.py
glupredkit/models/tcn.py
glupredkit/models/uva_padova.py
glupredkit/models/weighted_ridge.py
glupredkit/models/zero_order.py
glupredkit/parsers/IOBP2.py
glupredkit/parsers/__init__.py
glupredkit/parsers/apple_health.py
glupredkit/parsers/azt1d.py
glupredkit/parsers/base_parser.py
glupredkit/parsers/brist1d.py
glupredkit/parsers/ctr3.py
glupredkit/parsers/diatrend.py
glupredkit/parsers/hupa_ucm.py
glupredkit/parsers/nightscout.py
glupredkit/parsers/ohio_t1dm.py
glupredkit/parsers/open_aps.py
glupredkit/parsers/shanghai_t1dm.py
glupredkit/parsers/t1d_uom.py
glupredkit/parsers/t1dexi.py
glupredkit/parsers/tidepool.py
glupredkit/parsers/tidepool_dataset.py
glupredkit/plots/__init__.py
glupredkit/plots/all_metrics_table.py
glupredkit-1.0.31.dist-info/licenses/LICENSE.txt
glupredkit-1.0.31.dist-info/METADATA
glupredkit-1.0.31.dist-info/WHEEL
glupredkit-1.0.31.dist-info/entry_points.txt
glupredkit-1.0.31.dist-info/top_level.txt
glupredkit-1.0.31.dist-info/RECORD
