Metadata-Version: 2.4
Name: glupredkit
Version: 1.0.31
Summary: GluPredKit aims to make blood glucose model training and prediction more accessible.
Author: Miriam K. Wolff
Author-email: "Miriam K. Wolff" <miriamkwolff@outlook.com>
License: MIT
Project-URL: Homepage, https://github.com/miriamkw/GluPredKit
Project-URL: Bug Tracker, https://github.com/miriamkw/GluPredKit/issues
Requires-Python: >=3.9
License-File: LICENSE.txt
Requires-Dist: matplotlib
Requires-Dist: reportlab
Requires-Dist: svglib
Requires-Dist: seaborn
Requires-Dist: pandas
Requires-Dist: scikit-learn
Requires-Dist: tidepool-data-science-project
Requires-Dist: reportlab
Requires-Dist: numpy
Requires-Dist: aiohttp
Requires-Dist: click
Requires-Dist: dill
Requires-Dist: python-nightscout
Requires-Dist: error-grids
Requires-Dist: methcomp
Requires-Dist: wandb
Requires-Dist: python-dotenv
Requires-Dist: zipfile-deflate64-macos
Provides-Extra: heavy
Requires-Dist: xport; extra == "heavy"
Requires-Dist: tensorflow==2.14.0; extra == "heavy"
Requires-Dist: keras-tcn; extra == "heavy"
Requires-Dist: torch; extra == "heavy"
Requires-Dist: opsb-pyloopkit==0.1.0; extra == "heavy"
Requires-Dist: py_replay_bg; extra == "heavy"
Provides-Extra: test
Requires-Dist: pytest; extra == "test"
Requires-Dist: pytest-ordering; extra == "test"
Dynamic: author
Dynamic: license
Dynamic: license-file
Dynamic: provides-extra
Dynamic: requires-dist
Dynamic: requires-python
